Metadata-Version: 2.1
Name: testPyPichi
Version: 1.0.0
Summary: A package to test
Home-page: https://github.com/.....
Author: CBSUX
Author-email: cbs3307821258@qq.com
Classifier: Programming Language :: Python :: 3
Requires-Python: >=3.6
License-File: LICENSE
Requires-Dist: numpy==2.1.1
